{
    "英语": {
        "jobs": {
            "任务2": {
                "detail": "sdg"
            },
            "2345": {
                "detail": "5艾师傅"
            },
            "111发发1212": {
                "detail": "11但是故事"
            },
            "11111": {
                "detail": "232323"
            },
            "123123": {
                "detail": "123123"
            },
            "124": {
                "detail": "7777"
            },
            "sfsafa": {
                "detail": "asfsaf"
            },
            "4363": {
                "detail": "374347"
            }
        },
        "completed_dates": [
            "任务2",
            "2345",
            "111发发1212"
        ],
        "description": "234"
    },
    "健身": {
        "jobs": {
            "任务B1234": {
                "detail": "123"
            },
            "任务777": {
                "detail": "hahah777"
            },
            "任务4": {
                "detail": "436哥SGT是123"
            }
        },
        "completed_dates": [
            "任务B1234"
        ],
        "description": "123"
    }
}